carat/__init__.py
carat/annotations.py
carat/audio.py
carat/clustering.py
carat/display.py
carat/exceptions.py
carat/features.py
carat/util.py
carat/version.py
carat-0.1.1.dist-info/AUTHORS.md
carat-0.1.1.dist-info/LICENSE.md
carat-0.1.1.dist-info/METADATA
carat-0.1.1.dist-info/WHEEL
carat-0.1.1.dist-info/top_level.txt
carat-0.1.1.dist-info/RECORD
