Metadata-Version: 2.1
Name: carat
Version: 0.1.1
Summary: Computer-Aided Rhythm Analysis Toolbox
Home-page: http://github.com/mrocamora/carat
Author: Martín Rocamora
Author-email: rocamora@fing.edu.uy
License: MIT
Download-URL: http://github.com/mrocamora/carat/releases
Keywords: audio music sound
Platform: UNKNOWN
Classifier: Programming Language :: Python :: 3
Classifier: License :: OSI Approved :: MIT License
Classifier: Operating System :: OS Independent
Requires-Dist: audioread (>=2.0.0)
Requires-Dist: numpy (>=1.8.0)
Requires-Dist: scipy (>=1.0.0)
Requires-Dist: scikit-learn (>=0.14.0)
Requires-Dist: soundfile (>=0.9.0)
Requires-Dist: librosa (>=0.6.3)
Requires-Dist: matplotlib (>=2.0.0)
Requires-Dist: sounddevice (>=0.3.13)
Provides-Extra: display
Requires-Dist: matplotlib (>=1.5) ; extra == 'display'
Provides-Extra: docs
Requires-Dist: numpydoc ; extra == 'docs'
Requires-Dist: sphinx (!=1.3.1) ; extra == 'docs'
Requires-Dist: sphinx-rtd-theme ; extra == 'docs'
Requires-Dist: matplotlib (>=2.0.0) ; extra == 'docs'
Requires-Dist: sphinxcontrib-versioning (>=2.2.1) ; extra == 'docs'
Requires-Dist: sphinx-gallery ; extra == 'docs'
Provides-Extra: tests
Requires-Dist: matplotlib (>=2.1) ; extra == 'tests'
